{"neural": 1886, "neural network": 9, "deep": 4453, "deep learning": 16, "torch": 2398, "tensorflow": 1572, "cnn": 293, "rnn": 101, "gnn": 25, "attention": 252, "transformer": 545, "residual network": 0, "long short-term memory": 0, "long short term memory": 0, "lstm": 129, "gans": 28, "generative adversarial networks": 0, "convolutional": 191, "recurrent": 42, "feed forward": 0, "autoencoder": 67, "encoder-decoder": 16, "encoder decoder": 0, "hopfield network": 0, "boltzmann machine": 0, "kohonen network": 0, "capsule network": 0, "neural turing machine": 0, "liquid state machine": 0, "lsm": 28, "echo state machine": 0, "esm": 67, "gru": 53, "gated recurrent unit": 0}